src/__init__.py
src/operations.py
calculator_xyz_2025-0.1.0.dist-info/METADATA
calculator_xyz_2025-0.1.0.dist-info/WHEEL
calculator_xyz_2025-0.1.0.dist-info/top_level.txt
calculator_xyz_2025-0.1.0.dist-info/RECORD
